{"0G/USDT:USDT": {"data": {"symbol": "0G/USDT:USDT", "price": 0.6348, "rsi": 53.91, "status": "Neutral", "volume_usdt": 9144561.3362}, "ts": 1770927764.0114002, "prev_price": 0.6344}, "1/USDT:USDT": {"data": {"symbol": "1/USDT:USDT", "price": 0.000665, "rsi": 33.12, "status": "Neutral", "volume_usdt": 99471.70022}, "ts": 1770927764.0114002, "prev_price": 0.000668}, "1000000BABYDOGE/USDT:USDT": {"data": {"symbol": "1000000BABYDOGE/USDT:USDT", "price": 0.000381, "rsi": 49.21, "status": "Neutral", "volume_usdt": 201015.81}, "ts": 1770927764.0114002, "prev_price": 0.00038}, "1000000MOG/USDT:USDT": {"data": {"symbol": "1000000MOG/USDT:USDT", "price": 0.1637, "rsi": 45.95, "status": "Neutral", "volume_usdt": 368329.3907}, "ts": 1770927764.0114002, "prev_price": 0.1635}, "1000BONK/USDT:USDT": {"data": {"symbol": "1000BONK/USDT:USDT", "price": 0.005977, "rsi": 47.04, "status": "Neutral", "volume_usdt": 7846966.29}, "ts": 1770927764.0114002, "prev_price": 0.005981}, "1000BTT/USDT:USDT": {"data": {"symbol": "1000BTT/USDT:USDT", "price": 0.0003362, "rsi": 46.21, "status": "Neutral", "volume_usdt": 181444.812}, "ts": 1770927764.0114002, "prev_price": 0.0003362}, "1000RATS/USDT:USDT": {"data": {"symbol": "1000RATS/USDT:USDT", "price": 0.04431, "rsi": 44.13, "status": "Neutral", "volume_usdt": 111769.62}, "ts": 1770927764.0114002, "prev_price": 0.04434}, "114514/USDT:USDT": {"data": {"symbol": "114514/USDT:USDT", "price": 0.0002522, "rsi": 43.75, "status": "Neutral", "volume_usdt": 100890.20557}, "ts": 1770927764.0114002, "prev_price": 0.0002521}, "1INCH/USDT:USDT": {"data": {"symbol": "1INCH/USDT:USDT", "price": 0.0915, "rsi": 39.33, "status": "Neutral", "volume_usdt": 519715.5806}, "ts": 1770927764.0114002, "prev_price": 0.0914}, "2Z/USDT:USDT": {"data": {"symbol": "2Z/USDT:USDT", "price": 0.07771, "rsi": 53.97, "status": "Neutral", "volume_usdt": 1952.39}, "ts": 1770927764.0114002, "prev_price": 0.07773}, "3KDS/USDT:USDT": {"data": {"symbol": "3KDS/USDT:USDT", "price": 0.002775, "rsi": 42.97, "status": "Neutral", "volume_usdt": 107180.07}, "ts": 1770927764.0114002, "prev_price": 0.002803}, "4/USDT:USDT": {"data": {"symbol": "4/USDT:USDT", "price": 0.00944, "rsi": 53.41, "status": "Neutral", "volume_usdt": 212371.5442}, "ts": 1770927764.0114002, "prev_price": 0.00945}, "A/USDT:USDT": {"data": {"symbol": "A/USDT:USDT", "price": 0.0834, "rsi": 46.98, "status": "Neutral", "volume_usdt": 129031.5059}, "ts": 1770927764.0114002, "prev_price": 0.0834}, "A2Z/USDT:USDT": {"data": {"symbol": "A2Z/USDT:USDT", "price": 0.000945, "rsi": 51.39, "status": "Neutral", "volume_usdt": 108189.2221}, "ts": 1770927764.0114002, "prev_price": 0.000945}, "AAPLSTOCK/USDT:USDT": {"data": {"symbol": "AAPLSTOCK/USDT:USDT", "price": 261.83, "rsi": 13.58, "status": "Oversold", "volume_usdt": 501447.7782}, "ts": 1770927764.0114002, "prev_price": 261.92}, "AAVE/USDT:USDT": {"data": {"symbol": "AAVE/USDT:USDT", "price": 110.1, "rsi": 55.87, "status": "Neutral", "volume_usdt": 93426833.9163}, "ts": 1770927764.0114002, "prev_price": 110.11}, "ACE/USDT:USDT": {"data": {"symbol": "ACE/USDT:USDT", "price": 0.1641, "rsi": 40.04, "status": "Neutral", "volume_usdt": 515936.74032}, "ts": 1770927764.0114002, "prev_price": 0.1642}, "ACH/USDT:USDT": {"data": {"symbol": "ACH/USDT:USDT", "price": 0.007815, "rsi": 53.01, "status": "Neutral", "volume_usdt": 654681.368389}, "ts": 1770927764.0114002, "prev_price": 0.007825}, "ACNSTOCK/USDT:USDT": {"data": {"symbol": "ACNSTOCK/USDT:USDT", "price": 229.23, "rsi": 37.28, "status": "Neutral", "volume_usdt": 399894.68795}, "ts": 1770927764.0114002, "prev_price": 229.2}, "ACS/USDT:USDT": {"data": {"symbol": "ACS/USDT:USDT", "price": 0.0001904, "rsi": 49.94, "status": "Neutral", "volume_usdt": 100212.37663}, "ts": 1770927764.0114002, "prev_price": 0.0001903}, "ACT/USDT:USDT": {"data": {"symbol": "ACT/USDT:USDT", "price": 0.01402, "rsi": 46.47, "status": "Neutral", "volume_usdt": 267257.2699}, "ts": 1770927764.0114002, "prev_price": 0.01404}, "ACU/USDT:USDT": {"data": {"symbol": "ACU/USDT:USDT", "price": 0.1275, "rsi": 51.74, "status": "Neutral", "volume_usdt": 558456.51}, "ts": 1770927764.0114002, "prev_price": 0.1273}, "ACX/USDT:USDT": {"data": {"symbol": "ACX/USDT:USDT", "price": 0.03551, "rsi": 36.62, "status": "Neutral", "volume_usdt": 100710.99}, "ts": 1770927764.0114002, "prev_price": 0.0355}, "ADA/USDT:USDT": {"data": {"symbol": "ADA/USDT:USDT", "price": 0.26, "rsi": 47.81, "status": "Neutral", "volume_usdt": 204344087.9386}, "ts": 1770927783.4554598, "prev_price": 0.26}, "ADBESTOCK/USDT:USDT": {"data": {"symbol": "ADBESTOCK/USDT:USDT", "price": 261.22, "rsi": 59.7, "status": "Neutral", "volume_usdt": 120943.7346}, "ts": 1770927783.4554598, "prev_price": 260.96}, "AERGO/USDT:USDT": {"data": {"symbol": "AERGO/USDT:USDT", "price": 0.05648, "rsi": 46.11, "status": "Neutral", "volume_usdt": 134394.7986}, "ts": 1770927783.4554598, "prev_price": 0.05649}, "AERO/USDT:USDT": {"data": {"symbol": "AERO/USDT:USDT", "price": 0.29, "rsi": 44.29, "status": "Neutral", "volume_usdt": 753895.531}, "ts": 1770927783.4554598, "prev_price": 0.2899}, "AEVO/USDT:USDT": {"data": {"symbol": "AEVO/USDT:USDT", "price": 0.0259, "rsi": 40.28, "status": "Neutral", "volume_usdt": 151054.73}, "ts": 1770927783.4554598, "prev_price": 0.0259}, "AGI/USDT:USDT": {"data": {"symbol": "AGI/USDT:USDT", "price": 0.01151, "rsi": 47.01, "status": "Neutral", "volume_usdt": 117327.013}, "ts": 1770927783.4554598, "prev_price": 0.01151}, "AGLD/USDT:USDT": {"data": {"symbol": "AGLD/USDT:USDT", "price": 0.2273, "rsi": 57.68, "status": "Neutral", "volume_usdt": 150314.57}, "ts": 1770927783.4554598, "prev_price": 0.2274}, "AGT/USDT:USDT": {"data": {"symbol": "AGT/USDT:USDT", "price": 0.004665, "rsi": 43.41, "status": "Neutral", "volume_usdt": 127897.2226}, "ts": 1770927783.4554598, "prev_price": 0.004664}, "AI/USDT:USDT": {"data": {"symbol": "AI/USDT:USDT", "price": 0.02259, "rsi": 46.51, "status": "Neutral", "volume_usdt": 127128.34203}, "ts": 1770927783.4554598, "prev_price": 0.02256}, "AIA/USDT:USDT": {"data": {"symbol": "AIA/USDT:USDT", "price": 0.102, "rsi": 51.04, "status": "Neutral", "volume_usdt": 222792.84}, "ts": 1770927783.4554598, "prev_price": 0.102}, "AIAV/USDT:USDT": {"data": {"symbol": "AIAV/USDT:USDT", "price": 0.02569, "rsi": 41.24, "status": "Neutral", "volume_usdt": 98565.9352}, "ts": 1770927783.4554598, "prev_price": 0.02572}, "AIN/USDT:USDT": {"data": {"symbol": "AIN/USDT:USDT", "price": 0.03413, "rsi": 70.97, "status": "Overbought", "volume_usdt": 136331.56}, "ts": 1770927783.4554598, "prev_price": 0.03405}, "AIO/USDT:USDT": {"data": {"symbol": "AIO/USDT:USDT", "price": 0.0665, "rsi": 39.37, "status": "Neutral", "volume_usdt": 195627.2333}, "ts": 1770927783.4554598, "prev_price": 0.06648}, "AIOT/USDT:USDT": {"data": {"symbol": "AIOT/USDT:USDT", "price": 0.03111, "rsi": 39.35, "status": "Neutral", "volume_usdt": 149090.7858}, "ts": 1770927783.4554598, "prev_price": 0.03108}, "AIOZ/USDT:USDT": {"data": {"symbol": "AIOZ/USDT:USDT", "price": 0.0671, "rsi": 46.96, "status": "Neutral", "volume_usdt": 1747427.795}, "ts": 1770927783.4554598, "prev_price": 0.0671}, "AIXBT/USDT:USDT": {"data": {"symbol": "AIXBT/USDT:USDT", "price": 0.01972, "rsi": 52.3, "status": "Neutral", "volume_usdt": 473.24}, "ts": 1770927783.4554598, "prev_price": 0.01969}, "AKE/USDT:USDT": {"data": {"symbol": "AKE/USDT:USDT", "price": 0.0002381, "rsi": 64.92, "status": "Neutral", "volume_usdt": 127243.87}, "ts": 1770927783.4554598, "prev_price": 0.0002374}, "AKT/USDT:USDT": {"data": {"symbol": "AKT/USDT:USDT", "price": 0.3105, "rsi": 47.55, "status": "Neutral", "volume_usdt": 139890.3043}, "ts": 1770927764.0114002, "prev_price": 0.3102}, "ALCH/USDT:USDT": {"data": {"symbol": "ALCH/USDT:USDT", "price": 0.08152, "rsi": 48.6, "status": "Neutral", "volume_usdt": 428828.1718}, "ts": 1770927764.0114002, "prev_price": 0.08159}, "ALEO/USDT:USDT": {"data": {"symbol": "ALEO/USDT:USDT", "price": 0.0884, "rsi": 59.92, "status": "Neutral", "volume_usdt": 101083.8392}, "ts": 1770927764.0114002, "prev_price": 0.0883}, "ALGO/USDT:USDT": {"data": {"symbol": "ALGO/USDT:USDT", "price": 0.0905, "rsi": 48.41, "status": "Neutral", "volume_usdt": 7652125.2437}, "ts": 1770927764.0114002, "prev_price": 0.0904}, "ALICE/USDT:USDT": {"data": {"symbol": "ALICE/USDT:USDT", "price": 0.1103, "rsi": 45.81, "status": "Neutral", "volume_usdt": 129871.13362}, "ts": 1770927764.0114002, "prev_price": 0.1101}, "ALL/USDT:USDT": {"data": {"symbol": "ALL/USDT:USDT", "price": 0.465, "rsi": 49.85, "status": "Neutral", "volume_usdt": 105397.7694}, "ts": 1770927764.0114002, "prev_price": 0.465}, "ALLO/USDT:USDT": {"data": {"symbol": "ALLO/USDT:USDT", "price": 0.07426, "rsi": 38.44, "status": "Neutral", "volume_usdt": 628536.98285}, "ts": 1770927764.0114002, "prev_price": 0.0743}, "ALPINE/USDT:USDT": {"data": {"symbol": "ALPINE/USDT:USDT", "price": 0.4249, "rsi": 44.53, "status": "Neutral", "volume_usdt": 130185.2459}, "ts": 1770927783.4554598, "prev_price": 0.4251}, "ALT/USDT:USDT": {"data": {"symbol": "ALT/USDT:USDT", "price": 0.0085, "rsi": 47.54, "status": "Neutral", "volume_usdt": 318401.2867}, "ts": 1770927783.4554598, "prev_price": 0.00849}, "ALU/USDT:USDT": {"data": {"symbol": "ALU/USDT:USDT", "price": 0.004802, "rsi": 24.58, "status": "Oversold", "volume_usdt": 144548.11}, "ts": 1770927783.4554598, "prev_price": 0.004808}, "AMATSTOCK/USDT:USDT": {"data": {"symbol": "AMATSTOCK/USDT:USDT", "price": 329.46, "rsi": 36.18, "status": "Neutral", "volume_usdt": 709275.2062}, "ts": 1770927783.4554598, "prev_price": 329.63}, "AMDSTOCK/USDT:USDT": {"data": {"symbol": "AMDSTOCK/USDT:USDT", "price": 205.67, "rsi": 25.12, "status": "Oversold", "volume_usdt": 522266.5484}, "ts": 1770927783.4554598, "prev_price": 205.52}, "AMP/USDT:USDT": {"data": {"symbol": "AMP/USDT:USDT", "price": 0.001483, "rsi": 41.43, "status": "Neutral", "volume_usdt": 101038.13}, "ts": 1770927783.4554598, "prev_price": 0.001477}, "AMZNSTOCK/USDT:USDT": {"data": {"symbol": "AMZNSTOCK/USDT:USDT", "price": 198.87, "rsi": 26.28, "status": "Oversold", "volume_usdt": 268706.8697}, "ts": 1770927783.4554598, "prev_price": 198.84}, "ANIME/USDT:USDT": {"data": {"symbol": "ANIME/USDT:USDT", "price": 0.005614, "rsi": 54.7, "status": "Neutral", "volume_usdt": 221084.943794}, "ts": 1770927783.4554598, "prev_price": 0.005616}, "ANKR/USDT:USDT": {"data": {"symbol": "ANKR/USDT:USDT", "price": 0.004476, "rsi": 47.59, "status": "Neutral", "volume_usdt": 195745.83}, "ts": 1770927783.4554598, "prev_price": 0.00447}, "APE/USDT:USDT": {"data": {"symbol": "APE/USDT:USDT", "price": 0.1262, "rsi": 52.03, "status": "Neutral", "volume_usdt": 1571341.1472}, "ts": 1770927783.4554598, "prev_price": 0.1263}, "APEX/USDT:USDT": {"data": {"symbol": "APEX/USDT:USDT", "price": 0.2774, "rsi": 34.42, "status": "Neutral", "volume_usdt": 243719.5246}, "ts": 1770927783.4554598, "prev_price": 0.2771}, "API3/USDT:USDT": {"data": {"symbol": "API3/USDT:USDT", "price": 0.3038, "rsi": 39.36, "status": "Neutral", "volume_usdt": 514568.35}, "ts": 1770927783.4554598, "prev_price": 0.304}, "APR/USDT:USDT": {"data": {"symbol": "APR/USDT:USDT", "price": 0.08116, "rsi": 47.91, "status": "Neutral", "volume_usdt": 368865.62168}, "ts": 1770927783.4554598, "prev_price": 0.08087}, "APT/USDT:USDT": {"data": {"symbol": "APT/USDT:USDT", "price": 0.8993, "rsi": 33.08, "status": "Neutral", "volume_usdt": 55193441.43635}, "ts": 1770927783.4554598, "prev_price": 0.8999}, "AR/USDT:USDT": {"data": {"symbol": "AR/USDT:USDT", "price": 1.871, "rsi": 56.14, "status": "Neutral", "volume_usdt": 1502770.5942}, "ts": 1770927804.9128869, "prev_price": 1.873}, "ARB/USDT:USDT": {"data": {"symbol": "ARB/USDT:USDT", "price": 0.1092, "rsi": 46.52, "status": "Neutral", "volume_usdt": 38196504.2101}, "ts": 1770927804.9128869, "prev_price": 0.1093}, "ARCSOL/USDT:USDT": {"data": {"symbol": "ARCSOL/USDT:USDT", "price": 0.07552, "rsi": 59.53, "status": "Neutral", "volume_usdt": 506507.96}, "ts": 1770927804.9128869, "prev_price": 0.0754}, "ARIA/USDT:USDT": {"data": {"symbol": "ARIA/USDT:USDT", "price": 0.06622, "rsi": 46.18, "status": "Neutral", "volume_usdt": 270777.4387}, "ts": 1770927804.9128869, "prev_price": 0.06624}, "ARK/USDT:USDT": {"data": {"symbol": "ARK/USDT:USDT", "price": 0.1884, "rsi": 48.79, "status": "Neutral", "volume_usdt": 211657.82}, "ts": 1770927804.9128869, "prev_price": 0.1885}, "ARKM/USDT:USDT": {"data": {"symbol": "ARKM/USDT:USDT", "price": 0.1144, "rsi": 41.91, "status": "Neutral", "volume_usdt": 1639770.85}, "ts": 1770927804.9128869, "prev_price": 0.1143}, "ARMSTOCK/USDT:USDT": {"data": {"symbol": "ARMSTOCK/USDT:USDT", "price": 121.34, "rsi": 24.06, "status": "Oversold", "volume_usdt": 140445.9281}, "ts": 1770927804.9128869, "prev_price": 121.42}, "ARPA/USDT:USDT": {"data": {"symbol": "ARPA/USDT:USDT", "price": 0.00992, "rsi": 42.66, "status": "Neutral", "volume_usdt": 141473.50524}, "ts": 1770927804.9128869, "prev_price": 0.00993}, "ASMLSTOCK/USDT:USDT": {"data": {"symbol": "ASMLSTOCK/USDT:USDT", "price": 1411.09, "rsi": 36.87, "status": "Neutral", "volume_usdt": 113674.16}, "ts": 1770927804.9128869, "prev_price": 1410.82}, "ASP/USDT:USDT": {"data": {"symbol": "ASP/USDT:USDT", "price": 0.02943, "rsi": 63.6, "status": "Neutral", "volume_usdt": 175058.29}, "ts": 1770927804.9128869, "prev_price": 0.02943}, "ASR/USDT:USDT": {"data": {"symbol": "ASR/USDT:USDT", "price": 1.375, "rsi": 44.41, "status": "Neutral", "volume_usdt": 120125.443}, "ts": 1770927804.9128869, "prev_price": 1.375}, "ASTER/USDT:USDT": {"data": {"symbol": "ASTER/USDT:USDT", "price": 0.7095, "rsi": 52.23, "status": "Neutral", "volume_usdt": 112881628.13}, "ts": 1770927804.9128869, "prev_price": 0.7095}, "ASTR/USDT:USDT": {"data": {"symbol": "ASTR/USDT:USDT", "price": 0.007677, "rsi": 51.51, "status": "Neutral", "volume_usdt": 227826.98342}, "ts": 1770927804.9128869, "prev_price": 0.007683}, "AT/USDT:USDT": {"data": {"symbol": "AT/USDT:USDT", "price": 0.16007, "rsi": 48.65, "status": "Neutral", "volume_usdt": 181457.54758}, "ts": 1770927804.9128869, "prev_price": 0.16008}, "ATA/USDT:USDT": {"data": {"symbol": "ATA/USDT:USDT", "price": 0.01243, "rsi": 50.61, "status": "Neutral", "volume_usdt": 698762.5}, "ts": 1770927804.9128869, "prev_price": 0.01244}, "ATH/USDT:USDT": {"data": {"symbol": "ATH/USDT:USDT", "price": 0.005852, "rsi": 49.11, "status": "Neutral", "volume_usdt": 320460.60476}, "ts": 1770927804.9128869, "prev_price": 0.005855}, "ATOM/USDT:USDT": {"data": {"symbol": "ATOM/USDT:USDT", "price": 1.94, "rsi": 44.77, "status": "Neutral", "volume_usdt": 170498063.7744}, "ts": 1770927804.9128869, "prev_price": 1.943}, "AUCTION/USDT:USDT": {"data": {"symbol": "AUCTION/USDT:USDT", "price": 4.976, "rsi": 52.56, "status": "Neutral", "volume_usdt": 2129.73}, "ts": 1770927804.9128869, "prev_price": 4.982}, "AUD/USDT:USDT": {"data": {"symbol": "AUD/USDT:USDT", "price": 0.7094, "rsi": 42.07, "status": "Neutral", "volume_usdt": 275723.3551}, "ts": 1770927804.9128869, "prev_price": 0.7092}, "AUDIO/USDT:USDT": {"data": {"symbol": "AUDIO/USDT:USDT", "price": 0.02076, "rsi": 50.64, "status": "Neutral", "volume_usdt": 101089.21582}, "ts": 1770927804.9128869, "prev_price": 0.02088}, "AVA/USDT:USDT": {"data": {"symbol": "AVA/USDT:USDT", "price": 0.2166, "rsi": 44.18, "status": "Neutral", "volume_usdt": 147981.7804}, "ts": 1770927804.9128869, "prev_price": 0.2167}, "AVAAI/USDT:USDT": {"data": {"symbol": "AVAAI/USDT:USDT", "price": 0.0071, "rsi": 46.18, "status": "Neutral", "volume_usdt": 120192.0596}, "ts": 1770927804.9128869, "prev_price": 0.0071}, "AVAX/USDT:USDT": {"data": {"symbol": "AVAX/USDT:USDT", "price": 8.748, "rsi": 48.6, "status": "Neutral", "volume_usdt": 119684523.0801}, "ts": 1770927804.9128869, "prev_price": 8.754}, "AVGOSTOCK/USDT:USDT": {"data": {"symbol": "AVGOSTOCK/USDT:USDT", "price": 332.1, "rsi": 23.56, "status": "Oversold", "volume_usdt": 120534.8749}, "ts": 1770927804.9128869, "prev_price": 331.71}, "AVICI/USDT:USDT": {"data": {"symbol": "AVICI/USDT:USDT", "price": 1.169, "rsi": 42.69, "status": "Neutral", "volume_usdt": 100966.6234}, "ts": 1770927804.9128869, "prev_price": 1.166}, "AVL/USDT:USDT": {"data": {"symbol": "AVL/USDT:USDT", "price": 0.0418, "rsi": 61.0, "status": "Neutral", "volume_usdt": 236318.4911}, "ts": 1770927739.678188, "prev_price": 0.0419}, "AVNT/USDT:USDT": {"data": {"symbol": "AVNT/USDT:USDT", "price": 0.1941, "rsi": 53.64, "status": "Neutral", "volume_usdt": 1467831.6}, "ts": 1770927739.678188, "prev_price": 0.1941}, "AWE/USDT:USDT": {"data": {"symbol": "AWE/USDT:USDT", "price": 0.08563, "rsi": 57.16, "status": "Neutral", "volume_usdt": 234771.3425}, "ts": 1770927739.678188, "prev_price": 0.08575}, "AXL/USDT:USDT": {"data": {"symbol": "AXL/USDT:USDT", "price": 0.05861, "rsi": 42.44, "status": "Neutral", "volume_usdt": 237346.02}, "ts": 1770927739.678188, "prev_price": 0.05864}, "AXS/USDT:USDT": {"data": {"symbol": "AXS/USDT:USDT", "price": 1.387, "rsi": 38.0, "status": "Neutral", "volume_usdt": 16746841.866}, "ts": 1770927739.678188, "prev_price": 1.386}, "AZTEC/USDT:USDT": {"data": {"symbol": "AZTEC/USDT:USDT", "price": 0.02065, "rsi": 55.99, "status": "Neutral", "volume_usdt": 6132120.931}, "ts": 1770927783.4554598, "prev_price": 0.02064}, "B/USDT:USDT": {"data": {"symbol": "B/USDT:USDT", "price": 0.1492, "rsi": 39.59, "status": "Neutral", "volume_usdt": 425069.78}, "ts": 1770927783.4554598, "prev_price": 0.1491}, "B2/USDT:USDT": {"data": {"symbol": "B2/USDT:USDT", "price": 0.6922, "rsi": 48.48, "status": "Neutral", "volume_usdt": 132288.14}, "ts": 1770927783.4554598, "prev_price": 0.6927}, "B3/USDT:USDT": {"data": {"symbol": "B3/USDT:USDT", "price": 0.0004161, "rsi": 40.05, "status": "Neutral", "volume_usdt": 154121.16851}, "ts": 1770927783.4554598, "prev_price": 0.0004161}, "BABASTOCK/USDT:USDT": {"data": {"symbol": "BABASTOCK/USDT:USDT", "price": 157.66, "rsi": 36.72, "status": "Neutral", "volume_usdt": 305696.8701}, "ts": 1770927783.4554598, "prev_price": 157.64}, "BABY/USDT:USDT": {"data": {"symbol": "BABY/USDT:USDT", "price": 0.0133, "rsi": 44.16, "status": "Neutral", "volume_usdt": 153218.6152}, "ts": 1770927783.4554598, "prev_price": 0.01332}, "BACSTOCK/USDT:USDT": {"data": {"symbol": "BACSTOCK/USDT:USDT", "price": 52.74, "rsi": 34.12, "status": "Neutral", "volume_usdt": 109870.1577}, "ts": 1770927783.4554598, "prev_price": 52.74}, "BAN/USDT:USDT": {"data": {"symbol": "BAN/USDT:USDT", "price": 0.08703, "rsi": 68.58, "status": "Neutral", "volume_usdt": 244307.91}, "ts": 1770927783.4554598, "prev_price": 0.0871}, "BANANA/USDT:USDT": {"data": {"symbol": "BANANA/USDT:USDT", "price": 4.499, "rsi": 46.34, "status": "Neutral", "volume_usdt": 138169.9305}, "ts": 1770927783.4554598, "prev_price": 4.498}, "BANANAS31/USDT:USDT": {"data": {"symbol": "BANANAS31/USDT:USDT", "price": 0.004372, "rsi": 49.25, "status": "Neutral", "volume_usdt": 260502.002}, "ts": 1770927783.4554598, "prev_price": 0.004373}, "BAND/USDT:USDT": {"data": {"symbol": "BAND/USDT:USDT", "price": 0.24, "rsi": 45.5, "status": "Neutral", "volume_usdt": 208171.67}, "ts": 1770927783.4554598, "prev_price": 0.2402}, "BANK/USDT:USDT": {"data": {"symbol": "BANK/USDT:USDT", "price": 0.03253, "rsi": 56.05, "status": "Neutral", "volume_usdt": 297387.264}, "ts": 1770927783.4554598, "prev_price": 0.03257}, "BAR/USDT:USDT": {"data": {"symbol": "BAR/USDT:USDT", "price": 0.483, "rsi": 48.4, "status": "Neutral", "volume_usdt": 155783.978}, "ts": 1770927783.4554598, "prev_price": 0.479}, "BARD/USDT:USDT": {"data": {"symbol": "BARD/USDT:USDT", "price": 0.791, "rsi": 41.51, "status": "Neutral", "volume_usdt": 523229.85}, "ts": 1770927783.4554598, "prev_price": 0.791}, "BAS/USDT:USDT": {"data": {"symbol": "BAS/USDT:USDT", "price": 0.004853, "rsi": 56.36, "status": "Neutral", "volume_usdt": 284199.02}, "ts": 1770927783.4554598, "prev_price": 0.004851}, "BASTOCK/USDT:USDT": {"data": {"symbol": "BASTOCK/USDT:USDT", "price": 240.95, "rsi": 56.28, "status": "Neutral", "volume_usdt": 146105.1163}, "ts": 1770927783.4554598, "prev_price": 240.98}, "BAT/USDT:USDT": {"data": {"symbol": "BAT/USDT:USDT", "price": 0.1295, "rsi": 40.28, "status": "Neutral", "volume_usdt": 629853.4002}, "ts": 1770927783.4554598, "prev_price": 0.1296}, "BB/USDT:USDT": {"data": {"symbol": "BB/USDT:USDT", "price": 0.0316, "rsi": 47.99, "status": "Neutral", "volume_usdt": 359130.2542}, "ts": 1770927739.678188, "prev_price": 0.03162}, "BCH/USDT:USDT": {"data": {"symbol": "BCH/USDT:USDT", "price": 501.0, "rsi": 37.84, "status": "Neutral", "volume_usdt": 174281831.0526}, "ts": 1770927739.678188, "prev_price": 500.9}, "BDX/USDT:USDT": {"data": {"symbol": "BDX/USDT:USDT", "price": 0.0814, "rsi": 53.07, "status": "Neutral", "volume_usdt": 99840.589}, "ts": 1770927739.678188, "prev_price": 0.0814}, "BDXN/USDT:USDT": {"data": {"symbol": "BDXN/USDT:USDT", "price": 0.01094, "rsi": 35.93, "status": "Neutral", "volume_usdt": 117437.67088}, "ts": 1770927739.678188, "prev_price": 0.01099}, "BEAMX/USDT:USDT": {"data": {"symbol": "BEAMX/USDT:USDT", "price": 0.00236, "rsi": 45.44, "status": "Neutral", "volume_usdt": 150044.182}, "ts": 1770927739.678188, "prev_price": 0.002363}, "BEAT/USDT:USDT": {"data": {"symbol": "BEAT/USDT:USDT", "price": 0.2557, "rsi": 61.6, "status": "Neutral", "volume_usdt": 5492837.1}, "ts": 1770927739.678188, "prev_price": 0.256}, "BEL/USDT:USDT": {"data": {"symbol": "BEL/USDT:USDT", "price": 0.098, "rsi": 45.02, "status": "Neutral", "volume_usdt": 111471.6772}, "ts": 1770927739.678188, "prev_price": 0.0981}, "BERA/USDT:USDT": {"data": {"symbol": "BERA/USDT:USDT", "price": 0.708, "rsi": 44.27, "status": "Neutral", "volume_usdt": 55746726.02923}, "ts": 1770927739.678188, "prev_price": 0.7075}, "BIANRENSHENG/USDT:USDT": {"data": {"symbol": "BIANRENSHENG/USDT:USDT", "price": 0.09912, "rsi": 46.62, "status": "Neutral", "volume_usdt": 624321.3465}, "ts": 1770927764.0114002, "prev_price": 0.09915}, "BICO/USDT:USDT": {"data": {"symbol": "BICO/USDT:USDT", "price": 0.02467, "rsi": 46.93, "status": "Neutral", "volume_usdt": 135328.1}, "ts": 1770927764.0114002, "prev_price": 0.02467}, "BIGTIME/USDT:USDT": {"data": {"symbol": "BIGTIME/USDT:USDT", "price": 0.01489, "rsi": 54.34, "status": "Neutral", "volume_usdt": 274157.629}, "ts": 1770927764.0114002, "prev_price": 0.01492}, "BIO/USDT:USDT": {"data": {"symbol": "BIO/USDT:USDT", "price": 0.02372, "rsi": 39.25, "status": "Neutral", "volume_usdt": 265431.66998}, "ts": 1770927764.0114002, "prev_price": 0.02374}, "BIRB/USDT:USDT": {"data": {"symbol": "BIRB/USDT:USDT", "price": 0.1969, "rsi": 29.52, "status": "Oversold", "volume_usdt": 311377.71}, "ts": 1770927764.0114002, "prev_price": 0.1972}, "BLAST/USDT:USDT": {"data": {"symbol": "BLAST/USDT:USDT", "price": 0.0005769, "rsi": 59.81, "status": "Neutral", "volume_usdt": 133344.7893}, "ts": 1770927783.4554598, "prev_price": 0.0005769}, "BLESS/USDT:USDT": {"data": {"symbol": "BLESS/USDT:USDT", "price": 0.005606, "rsi": 44.87, "status": "Neutral", "volume_usdt": 8296405.91936}, "ts": 1770927783.4554598, "prev_price": 0.005585}, "BLOCK/USDT:USDT": {"data": {"symbol": "BLOCK/USDT:USDT", "price": 0.00706, "rsi": 39.56, "status": "Neutral", "volume_usdt": 101082.2515}, "ts": 1770927783.4554598, "prev_price": 0.00697}, "BLUAI/USDT:USDT": {"data": {"symbol": "BLUAI/USDT:USDT", "price": 0.006606, "rsi": 45.0, "status": "Neutral", "volume_usdt": 404273.13}, "ts": 1770927783.4554598, "prev_price": 0.006606}, "BLUR/USDT:USDT": {"data": {"symbol": "BLUR/USDT:USDT", "price": 0.02045, "rsi": 54.94, "status": "Neutral", "volume_usdt": 197918.2885}, "ts": 1770927783.4554598, "prev_price": 0.02048}, "BMT/USDT:USDT": {"data": {"symbol": "BMT/USDT:USDT", "price": 0.01673, "rsi": 48.26, "status": "Neutral", "volume_usdt": 126225.1871}, "ts": 1770927739.678188, "prev_price": 0.01675}, "BNB/USDT:USDT": {"data": {"symbol": "BNB/USDT:USDT", "price": 607.1, "rsi": 45.22, "status": "Neutral", "volume_usdt": 34725929.258}, "ts": 1770927739.678188, "prev_price": 606.8}, "BNT/USDT:USDT": {"data": {"symbol": "BNT/USDT:USDT", "price": 0.2754, "rsi": 39.99, "status": "Neutral", "volume_usdt": 109887.68}, "ts": 1770927739.678188, "prev_price": 0.2755}, "BOBA/USDT:USDT": {"data": {"symbol": "BOBA/USDT:USDT", "price": 0.02276, "rsi": 39.94, "status": "Neutral", "volume_usdt": 449509.72389}, "ts": 1770927739.678188, "prev_price": 0.02275}, "BOME/USDT:USDT": {"data": {"symbol": "BOME/USDT:USDT", "price": 0.0003904, "rsi": 49.55, "status": "Neutral", "volume_usdt": 430401.1875}, "ts": 1770927739.678188, "prev_price": 0.0003905}, "BR/USDT:USDT": {"data": {"symbol": "BR/USDT:USDT", "price": 0.05691, "rsi": 34.78, "status": "Neutral", "volume_usdt": 104596.5959}, "ts": 1770927739.678188, "prev_price": 0.05699}, "BRETT/USDT:USDT": {"data": {"symbol": "BRETT/USDT:USDT", "price": 0.00704, "rsi": 50.42, "status": "Neutral", "volume_usdt": 768157.977}, "ts": 1770927739.678188, "prev_price": 0.00705}, "BREV/USDT:USDT": {"data": {"symbol": "BREV/USDT:USDT", "price": 0.1541, "rsi": 61.26, "status": "Neutral", "volume_usdt": 1272102.72}, "ts": 1770927739.678188, "prev_price": 0.1542}, "BRL/USDT:USDT": {"data": {"symbol": "BRL/USDT:USDT", "price": 0.1921, "rsi": 38.87, "status": "Neutral", "volume_usdt": 167844.206}, "ts": 1770927739.678188, "prev_price": 0.1921}, "BROCCOLI/USDT:USDT": {"data": {"symbol": "BROCCOLI/USDT:USDT", "price": 0.0131, "rsi": 54.42, "status": "Neutral", "volume_usdt": 219857.5324}, "ts": 1770927739.678188, "prev_price": 0.01309}, "BROCCOLIF3B/USDT:USDT": {"data": {"symbol": "BROCCOLIF3B/USDT:USDT", "price": 0.003791, "rsi": 45.82, "status": "Neutral", "volume_usdt": 112388.29056}, "ts": 1770927739.678188, "prev_price": 0.003792}, "BSU/USDT:USDT": {"data": {"symbol": "BSU/USDT:USDT", "price": 0.13167, "rsi": 52.31, "status": "Neutral", "volume_usdt": 275515.87}, "ts": 1770927739.678188, "prev_price": 0.13163}, "BSV/USDT:USDT": {"data": {"symbol": "BSV/USDT:USDT", "price": 14.56, "rsi": 59.83, "status": "Neutral", "volume_usdt": 254410.0247}, "ts": 1770927739.678188, "prev_price": 14.57}, "BTC/USDT:USDT": {"data": {"symbol": "BTC/USDT:USDT", "price": 65596.6, "rsi": 35.52, "status": "Neutral", "volume_usdt": 1768474801.47}, "ts": 1770927739.678188, "prev_price": 65618.1}, "BTR/USDT:USDT": {"data": {"symbol": "BTR/USDT:USDT", "price": 0.14028, "rsi": 64.85, "status": "Neutral", "volume_usdt": 8330968.8289}, "ts": 1770927739.678188, "prev_price": 0.13985}, "BTX/USDT:USDT": {"data": {"symbol": "BTX/USDT:USDT", "price": 0.00943, "rsi": 50.03, "status": "Neutral", "volume_usdt": 100352.5672}, "ts": 1770927739.678188, "prev_price": 0.00943}, "BUILDONBOB/USDT:USDT": {"data": {"symbol": "BUILDONBOB/USDT:USDT", "price": 0.00674, "rsi": 29.04, "status": "Oversold", "volume_usdt": 117844.669}, "ts": 1770927739.678188, "prev_price": 0.00673}, "BULLA/USDT:USDT": {"data": {"symbol": "BULLA/USDT:USDT", "price": 0.02429, "rsi": 36.82, "status": "Neutral", "volume_usdt": 237866.97}, "ts": 1770927783.4554598, "prev_price": 0.02431}, "C/USDT:USDT": {"data": {"symbol": "C/USDT:USDT", "price": 0.053, "rsi": 51.32, "status": "Neutral", "volume_usdt": 123183.625}, "ts": 1770927783.4554598, "prev_price": 0.053}, "C98/USDT:USDT": {"data": {"symbol": "C98/USDT:USDT", "price": 0.03213, "rsi": 63.99, "status": "Neutral", "volume_usdt": 593777.02}, "ts": 1770927783.4554598, "prev_price": 0.0322}, "CAD/USDT:USDT": {"data": {"symbol": "CAD/USDT:USDT", "price": 0.7345, "rsi": 38.61, "status": "Neutral", "volume_usdt": 194075.9255}, "ts": 1770927783.4554598, "prev_price": 0.735}, "CAI/USDT:USDT": {"data": {"symbol": "CAI/USDT:USDT", "price": 0.0377, "rsi": 44.76, "status": "Neutral", "volume_usdt": 104019.3082}, "ts": 1770927783.4554598, "prev_price": 0.0374}, "CAKE/USDT:USDT": {"data": {"symbol": "CAKE/USDT:USDT", "price": 1.2831, "rsi": 40.92, "status": "Neutral", "volume_usdt": 5811910.4}, "ts": 1770927783.4554598, "prev_price": 1.2831}, "CAMP/USDT:USDT": {"data": {"symbol": "CAMP/USDT:USDT", "price": 0.004715, "rsi": 80.24, "status": "Overbought", "volume_usdt": 278338.94281}, "ts": 1770927783.4554598, "prev_price": 0.004717}, "CARV/USDT:USDT": {"data": {"symbol": "CARV/USDT:USDT", "price": 0.06487, "rsi": 60.99, "status": "Neutral", "volume_usdt": 111824.6631}, "ts": 1770927719.3737936, "prev_price": 0.06477}, "CAT/USDT:USDT": {"data": {"symbol": "CAT/USDT:USDT", "price": 1.8e-06, "rsi": 49.17, "status": "Neutral", "volume_usdt": 131347.6907}, "ts": 1770927719.3737936, "prev_price": 1.8e-06}, "CATI/USDT:USDT": {"data": {"symbol": "CATI/USDT:USDT", "price": 0.04127, "rsi": 50.58, "status": "Neutral", "volume_usdt": 229.67}, "ts": 1770927719.3737936, "prev_price": 0.04124}, "CATSTOCK/USDT:USDT": {"data": {"symbol": "CATSTOCK/USDT:USDT", "price": 763.57, "rsi": 42.03, "status": "Neutral", "volume_usdt": 117791.35342}, "ts": 1770927719.3737936, "prev_price": 762.22}, "CC/USDT:USDT": {"data": {"symbol": "CC/USDT:USDT", "price": 0.16405, "rsi": 45.41, "status": "Neutral", "volume_usdt": 1350852.06}, "ts": 1770927719.3737936, "prev_price": 0.16343}, "CELO/USDT:USDT": {"data": {"symbol": "CELO/USDT:USDT", "price": 0.0798, "rsi": 40.46, "status": "Neutral", "volume_usdt": 372187.1875}, "ts": 1770927719.3737936, "prev_price": 0.0798}, "CELR/USDT:USDT": {"data": {"symbol": "CELR/USDT:USDT", "price": 0.002555, "rsi": 49.56, "status": "Neutral", "volume_usdt": 119320.303161}, "ts": 1770927719.3737936, "prev_price": 0.002553}, "CETUS/USDT:USDT": {"data": {"symbol": "CETUS/USDT:USDT", "price": 0.01545, "rsi": 48.41, "status": "Neutral", "volume_usdt": 76361.1246}, "ts": 1770927764.0114002, "prev_price": 0.01546}, "CFX/USDT:USDT": {"data": {"symbol": "CFX/USDT:USDT", "price": 0.04791, "rsi": 57.2, "status": "Neutral", "volume_usdt": 971283.57102}, "ts": 1770927649.49933, "prev_price": 0.04791}, "CGN/USDT:USDT": {"data": {"symbol": "CGN/USDT:USDT", "price": 0.003053, "rsi": 55.86, "status": "Neutral", "volume_usdt": 100415.8971}, "ts": 1770927649.49933, "prev_price": 0.003011}, "CGPT/USDT:USDT": {"data": {"symbol": "CGPT/USDT:USDT", "price": 0.02101, "rsi": 47.75, "status": "Neutral", "volume_usdt": 153698.1227}, "ts": 1770927430.3203166, "prev_price": 0.02102}, "CHEEMS/USDT:USDT": {"data": {"symbol": "CHEEMS/USDT:USDT", "price": 5.4e-07, "rsi": 59.39, "status": "Neutral", "volume_usdt": 152153.361}, "ts": 1770927430.3203166, "prev_price": 5.4e-07}, "CHF/USDT:USDT": {"data": {"symbol": "CHF/USDT:USDT", "price": 1.2994, "rsi": 49.91, "status": "Neutral", "volume_usdt": 106193.1946}, "ts": 1770927430.3203166, "prev_price": 1.2994}, "CHILLGUY/USDT:USDT": {"data": {"symbol": "CHILLGUY/USDT:USDT", "price": 0.0098, "rsi": 47.45, "status": "Neutral", "volume_usdt": 145585.5886}, "ts": 1770927430.3203166, "prev_price": 0.00979}, "CHR/USDT:USDT": {"data": {"symbol": "CHR/USDT:USDT", "price": 0.02634, "rsi": 41.12, "status": "Neutral", "volume_usdt": 127366.1471}, "ts": 1770927430.3203166, "prev_price": 0.02637}, "CHZ/USDT:USDT": {"data": {"symbol": "CHZ/USDT:USDT", "price": 0.03966, "rsi": 50.24, "status": "Neutral", "volume_usdt": 18702832.52181}, "ts": 1770927430.3203166, "prev_price": 0.03968}, "CITY/USDT:USDT": {"data": {"symbol": "CITY/USDT:USDT", "price": 0.576, "rsi": 55.66, "status": "Neutral", "volume_usdt": 101140.157}, "ts": 1770927430.3203166, "prev_price": 0.574}, "CKB/USDT:USDT": {"data": {"symbol": "CKB/USDT:USDT", "price": 0.001609, "rsi": 38.49, "status": "Neutral", "volume_usdt": 363064.646}, "ts": 1770927430.3203166, "prev_price": 0.001607}, "CLANKER/USDT:USDT": {"data": {"symbol": "CLANKER/USDT:USDT", "price": 33.65, "rsi": 38.21, "status": "Neutral", "volume_usdt": 396992.7653}, "ts": 1770927430.3203166, "prev_price": 33.52}, "CLAWDONBASE/USDT:USDT": {"data": {"symbol": "CLAWDONBASE/USDT:USDT", "price": 6.077e-05, "rsi": 43.36, "status": "Neutral", "volume_usdt": 103549.0386}, "ts": 1770927430.3203166, "prev_price": 6.058e-05}, "CLAWNCH/USDT:USDT": {"data": {"symbol": "CLAWNCH/USDT:USDT", "price": 0.000129, "rsi": 35.44, "status": "Neutral", "volume_usdt": 343056.9454}, "ts": 1770926382.384248, "prev_price": 0.0001318}, "CLO/USDT:USDT": {"data": {"symbol": "CLO/USDT:USDT", "price": 0.0794, "rsi": 64.81, "status": "Neutral", "volume_usdt": 1834408.625}, "ts": 1770926382.384248, "prev_price": 0.0819}, "CLOUD/USDT:USDT": {"data": {"symbol": "CLOUD/USDT:USDT", "price": 0.04116, "rsi": 45.01, "status": "Neutral", "volume_usdt": 104958.6807}, "ts": 1770926382.384248, "prev_price": 0.04101}, "COAI/USDT:USDT": {"data": {"symbol": "COAI/USDT:USDT", "price": 0.3094, "rsi": 52.23, "status": "Neutral", "volume_usdt": 637005.204}, "ts": 1770926382.384248, "prev_price": 0.3106}, "COINBASE/USDT:USDT": {"data": {"symbol": "COINBASE/USDT:USDT", "price": 142.38, "rsi": 29.61, "status": "Oversold", "volume_usdt": 384387.382}, "ts": 1770926382.384248, "prev_price": 142.78}, "COLLECT/USDT:USDT": {"data": {"symbol": "COLLECT/USDT:USDT", "price": 0.06398, "rsi": 54.23, "status": "Neutral", "volume_usdt": 509361.093}, "ts": 1770926382.384248, "prev_price": 0.06292}, "COMP/USDT:USDT": {"data": {"symbol": "COMP/USDT:USDT", "price": 15.53, "rsi": 41.86, "status": "Neutral", "volume_usdt": 444678.6037}, "ts": 1770926382.384248, "prev_price": 15.66}, "COOK/USDT:USDT": {"data": {"symbol": "COOK/USDT:USDT", "price": 0.003342, "rsi": 60.72, "status": "Neutral", "volume_usdt": 143740.755}, "ts": 1770925393.242835, "prev_price": 0.003346}, "COOKIE/USDT:USDT": {"data": {"symbol": "COOKIE/USDT:USDT", "price": 0.01966, "rsi": 55.54, "status": "Neutral", "volume_usdt": 128231.19}, "ts": 1770925393.242835, "prev_price": 0.01969}, "COPPER/USDT:USDT": {"data": {"symbol": "COPPER/USDT:USDT", "price": 5.842, "rsi": 25.34, "status": "Oversold", "volume_usdt": 539569.1508}, "ts": 1770925393.242835, "prev_price": 5.843}, "CORE/USDT:USDT": {"data": {"symbol": "CORE/USDT:USDT", "price": 0.08436, "rsi": 52.79, "status": "Neutral", "volume_usdt": 285821.43872}, "ts": 1770925393.242835, "prev_price": 0.08464}, "COS/USDT:USDT": {"data": {"symbol": "COS/USDT:USDT", "price": 0.001057, "rsi": 50.76, "status": "Neutral", "volume_usdt": 103500.8008}, "ts": 1770925393.242835, "prev_price": 0.001059}, "COSTSTOCK/USDT:USDT": {"data": {"symbol": "COSTSTOCK/USDT:USDT", "price": 1008.36, "rsi": 79.49, "status": "Overbought", "volume_usdt": 157338.00954}, "ts": 1770925393.242835, "prev_price": 1008.29}, "COTI/USDT:USDT": {"data": {"symbol": "COTI/USDT:USDT", "price": 0.012, "rsi": 52.73, "status": "Neutral", "volume_usdt": 294362.23296}, "ts": 1770925393.242835, "prev_price": 0.01205}, "COW/USDT:USDT": {"data": {"symbol": "COW/USDT:USDT", "price": 0.1879, "rsi": 47.19, "status": "Neutral", "volume_usdt": 242176.19}, "ts": 1770925393.242835, "prev_price": 0.189}, "CRCLSTOCK/USDT:USDT": {"data": {"symbol": "CRCLSTOCK/USDT:USDT", "price": 57.52, "rsi": 48.32, "status": "Neutral", "volume_usdt": 279870.4304}, "ts": 1770925393.242835, "prev_price": 57.46}, "CRMSTOCK/USDT:USDT": {"data": {"symbol": "CRMSTOCK/USDT:USDT", "price": 182.81, "rsi": 36.82, "status": "Neutral", "volume_usdt": 115101.6162}, "ts": 1770925393.242835, "prev_price": 182.62}, "CRO/USDT:USDT": {"data": {"symbol": "CRO/USDT:USDT", "price": 0.07679, "rsi": 49.06, "status": "Neutral", "volume_usdt": 2793412.6885}, "ts": 1770925393.242835, "prev_price": 0.07711}, "CROSS/USDT:USDT": {"data": {"symbol": "CROSS/USDT:USDT", "price": 0.10214, "rsi": 49.15, "status": "Neutral", "volume_usdt": 109832.1564}, "ts": 1770925393.242835, "prev_price": 0.10225}, "CRV/USDT:USDT": {"data": {"symbol": "CRV/USDT:USDT", "price": 0.2375, "rsi": 52.95, "status": "Neutral", "volume_usdt": 3747278.29}, "ts": 1770924990.6002626, "prev_price": 0.2356}, "CSCOSTOCK/USDT:USDT": {"data": {"symbol": "CSCOSTOCK/USDT:USDT", "price": 75.98, "rsi": 20.79, "status": "Oversold", "volume_usdt": 950414.4172}, "ts": 1770924990.6002626, "prev_price": 76.16}, "CSPR/USDT:USDT": {"data": {"symbol": "CSPR/USDT:USDT", "price": 0.003326, "rsi": 52.01, "status": "Neutral", "volume_usdt": 127990.565787}, "ts": 1770924552.421584, "prev_price": 0.00333}, "CTC/USDT:USDT": {"data": {"symbol": "CTC/USDT:USDT", "price": 0.1483, "rsi": 52.81, "status": "Neutral", "volume_usdt": 404306.97}, "ts": 1770924552.421584, "prev_price": 0.1484}, "CTK/USDT:USDT": {"data": {"symbol": "CTK/USDT:USDT", "price": 0.207, "rsi": 47.71, "status": "Neutral", "volume_usdt": 104902.6464}, "ts": 1770924552.421584, "prev_price": 0.2068}, "CTSI/USDT:USDT": {"data": {"symbol": "CTSI/USDT:USDT", "price": 0.02618, "rsi": 49.62, "status": "Neutral", "volume_usdt": 105380.05}, "ts": 1770924552.421584, "prev_price": 0.02615}, "CVC/USDT:USDT": {"data": {"symbol": "CVC/USDT:USDT", "price": 0.03237, "rsi": 44.4, "status": "Neutral", "volume_usdt": 112932.15673}, "ts": 1770924552.421584, "prev_price": 0.03235}, "CVNASTOCK/USDT:USDT": {"data": {"symbol": "CVNASTOCK/USDT:USDT", "price": 345.75, "rsi": 33.51, "status": "Neutral", "volume_usdt": 171976.8826}, "ts": 1770924552.421584, "prev_price": 347.43}, "CVX/USDT:USDT": {"data": {"symbol": "CVX/USDT:USDT", "price": 1.928, "rsi": 52.49, "status": "Neutral", "volume_usdt": 710195.25}, "ts": 1770924552.421584, "prev_price": null}, "CYBER/USDT:USDT": {"data": {"symbol": "CYBER/USDT:USDT", "price": 0.5861, "rsi": 60.68, "status": "Neutral", "volume_usdt": 110474.026}, "ts": 1770924552.421584, "prev_price": null}, "CYPR/USDT:USDT": {"data": {"symbol": "CYPR/USDT:USDT", "price": 0.01587, "rsi": 50.64, "status": "Neutral", "volume_usdt": 99764.4344}, "ts": 1770924552.421584, "prev_price": null}}